pyidr/__init__.py
pyidr/__init__.py.orig
pyidr/_base.py
pyidr/_idr.py
pyidr/_interpolations.py
pyidr/_stats.py
pyidr-0.1.1.dist-info/LICENSE
pyidr-0.1.1.dist-info/WHEEL
pyidr-0.1.1.dist-info/METADATA
pyidr-0.1.1.dist-info/RECORD
